HalChat.py
HalChatAPI.py
HalChatEncryption.py
HalChatWS.py
HalEncryption.py
HalHash.py
__init__.py
halchat-0.0.4.3.dist-info/licenses/LICENSE
halchat-0.0.4.3.dist-info/METADATA
halchat-0.0.4.3.dist-info/WHEEL
halchat-0.0.4.3.dist-info/top_level.txt
halchat-0.0.4.3.dist-info/RECORD
